notification_py/__init__.py
notification_py/custom_types.py
notification_py/main.py
notification_py/services/__init__.py
notification_py/services/discord.py
notification_py/services/email.py
notification_py/services/slack.py
notification_py-1.0.5.dist-info/LICENSE
notification_py-1.0.5.dist-info/METADATA
notification_py-1.0.5.dist-info/WHEEL
notification_py-1.0.5.dist-info/RECORD
